fast_simplification/__init__.py
fast_simplification/_replay.cpython-310-x86_64-linux-gnu.so
fast_simplification/_simplify.cpython-310-x86_64-linux-gnu.so
fast_simplification/_version.py
fast_simplification/fast_simplification.py
fast_simplification/replay.py
fast_simplification/simplify.py
fast_simplification/utils.py
fast_simplification-0.1.13.dist-info/METADATA
fast_simplification-0.1.13.dist-info/WHEEL
fast_simplification-0.1.13.dist-info/top_level.txt
fast_simplification-0.1.13.dist-info/RECORD
fast_simplification-0.1.13.dist-info/licenses/LICENSE
